gridtk/__init__.py
gridtk/__main__.py
gridtk/cli.py
gridtk/manager.py
gridtk/models.py
gridtk/tools.py
gridtk-3.0.1.dist-info/METADATA
gridtk-3.0.1.dist-info/WHEEL
gridtk-3.0.1.dist-info/entry_points.txt
gridtk-3.0.1.dist-info/licenses/COPYING
gridtk-3.0.1.dist-info/RECORD
