Metadata-Version: 2.3
Name: gridtk
Version: 3.0.1
Summary: GridTK: Slurm Job Management for Humans
Project-URL: documentation, https://gridtk.readthedocs.io/en/stable/
Project-URL: homepage, https://pypi.org/project/gridtk
Project-URL: repository, https://github.com/idiap/gridtk
Project-URL: changelog, https://github.com/idiap/gridtk/releases
Author-email: Amir Mohamamdi <amir.mohammadi@idiap.ch>, Andre Anjos <andre.anjos@idiap.ch>, Manuel Guenther <manuel.guenther@idiap.ch>
License-Expression: GPL-3.0-or-later
License-File: COPYING
Classifier: Development Status :: 5 - Production/Stable
Classifier: Intended Audience :: Developers
Classifier: License :: OSI Approved :: GNU General Public License v3 (GPLv3)
Classifier: Natural Language :: English
Classifier: Programming Language :: Python :: 3
Classifier: Topic :: System :: Distributed Computing
Requires-Python: >=3.9
Requires-Dist: click~=8.1
Requires-Dist: sqlalchemy~=2.0
Requires-Dist: tabulate~=0.9.0
Provides-Extra: dev
Requires-Dist: coverage; extra == 'dev'
Requires-Dist: furo; extra == 'dev'
Requires-Dist: myst-parser; extra == 'dev'
Requires-Dist: pre-commit; extra == 'dev'
Requires-Dist: pytest; extra == 'dev'
Requires-Dist: pytest-cov; extra == 'dev'
Requires-Dist: ruff; extra == 'dev'
Requires-Dist: sphinx; extra == 'dev'
Requires-Dist: sphinx-autodoc-typehints; extra == 'dev'
Requires-Dist: sphinx-copybutton; extra == 'dev'
Requires-Dist: sphinx-inline-tabs; extra == 'dev'
Provides-Extra: doc
Requires-Dist: furo; extra == 'doc'
Requires-Dist: myst-parser; extra == 'doc'
Requires-Dist: sphinx; extra == 'doc'
Requires-Dist: sphinx-autodoc-typehints; extra == 'doc'
Requires-Dist: sphinx-copybutton; extra == 'doc'
Requires-Dist: sphinx-inline-tabs; extra == 'doc'
Provides-Extra: test
Requires-Dist: coverage; extra == 'test'
Requires-Dist: pytest; extra == 'test'
Requires-Dist: pytest-cov; extra == 'test'
